odoo/addons/cms_info/README.rst
odoo/addons/cms_info/__init__.py
odoo/addons/cms_info/__manifest__.py
odoo/addons/cms_info/i18n/ca.po
odoo/addons/cms_info/i18n/cms_info.pot
odoo/addons/cms_info/i18n/es.po
odoo/addons/cms_info/models/__init__.py
odoo/addons/cms_info/models/cms_mixin.py
odoo/addons/cms_info/models/website_mixin.py
odoo/addons/cms_info/readme/CONTRIBUTORS.rst
odoo/addons/cms_info/readme/DESCRIPTION.rst
odoo/addons/cms_info/readme/HISTORY.rst
odoo/addons/cms_info/readme/ROADMAP.rst
odoo/addons/cms_info/readme/USAGE.rst
odoo/addons/cms_info/static/description/icon.png
odoo/addons/cms_info/static/description/index.html
odoo/addons/cms_info/tests/__init__.py
odoo/addons/cms_info/tests/fake_models.py
odoo/addons/cms_info/tests/test_info_mixin.py
odoo13_addon_cms_info-13.0.1.0.1.dist-info/METADATA
odoo13_addon_cms_info-13.0.1.0.1.dist-info/WHEEL
odoo13_addon_cms_info-13.0.1.0.1.dist-info/top_level.txt
odoo13_addon_cms_info-13.0.1.0.1.dist-info/RECORD
